README.rst
setup.py
aio/__init__.py
aio.manhole.server.egg-info/PKG-INFO
aio.manhole.server.egg-info/SOURCES.txt
aio.manhole.server.egg-info/dependency_links.txt
aio.manhole.server.egg-info/namespace_packages.txt
aio.manhole.server.egg-info/not-zip-safe
aio.manhole.server.egg-info/requires.txt
aio.manhole.server.egg-info/top_level.txt
aio/manhole/__init__.py
aio/manhole/server/__init__.py
aio/manhole/server/tests/__init__.py